ludvig/__init__.py
ludvig/__main__.py
ludvig/_format.py
ludvig/_help.py
ludvig/_types.py
ludvig/config.py
ludvig/utils.py
ludvig/commands/__init__.py
ludvig/commands/filesystem.py
ludvig/commands/git.py
ludvig/commands/image.py
ludvig/commands/rules.py
ludvig/commands/vulndb.py
ludvig/outputs/__init__.py
ludvig/outputs/_sarif.py
ludvig/parsers/dotnet_deps.py
ludvig/providers/__init__.py
ludvig/providers/_containerprovider.py
ludvig/providers/_filesystemprovider.py
ludvig/providers/_gitprovider.py
ludvig/providers/_providers.py
ludvig/providers/_docker/_client.py
ludvig/providers/_docker/_definitions.py
ludvig/providers/_docker/_main.py
ludvig/providers/_git/__init__.py
ludvig/providers/_git/_definitions.py
ludvig/rules/__init__.py
ludvig/rules/_loader.py
ludvig/rules/yara/fileformats/compressed.yar
ludvig/rules/yara/sbom/dotnet_deps.yar
ludvig/rules/yara/secrets/global.yar
ludvig/rules/yara/webshells/php_in_images.yar
ludvig/rules/yara/webshells/webshell_php.yar
ludvig/sbom/generator.py
ludvig/sbom/dotnet/__init__.py
ludvig/sbom/dotnet/dependencies.py
ludvig/sbom/dotnet/dependencies_file.py
ludvig/scanners/__init__.py
ludvig/scanners/_common.py
ludvig/scanners/_secrets.py
ludvig/scanners/_vulndb.py
ludvig/vulndb/__init__.py
ludvig/vulndb/_advisory.py
ludvig/vulndb/_db.py
ludvig/vulndb/_osv.py
ludvig/vulndb/ingesters/__init__.py
ludvig/vulndb/ingesters/_github_advisories.py
ludvig-0.8.4.dist-info/METADATA
ludvig-0.8.4.dist-info/WHEEL
ludvig-0.8.4.dist-info/entry_points.txt
ludvig-0.8.4.dist-info/licenses/LICENSE
ludvig-0.8.4.dist-info/RECORD
