Metadata-Version: 2.1
Name: ludvig
Version: 0.8.4
Summary: A simple vulnerability scanner
Project-URL: Homepage, https://github.com/frodehus/ludvig
Project-URL: Bug Tracker, https://github.com/frodehus/ludvig/issues
Author-email: Frode Hus <frode@frodehus.dev>
License-File: LICENSE
Classifier: License :: OSI Approved :: MIT License
Classifier: Operating System :: OS Independent
Classifier: Programming Language :: Python :: 3
Requires-Python: >=3.7
Requires-Dist: cyclonedx-python-lib>=5.1.1
Requires-Dist: defusedxml>=0.7.1
Requires-Dist: jschema-to-python>=1.2.3
Requires-Dist: knack>=0.11.0
Requires-Dist: packageurl-python>=0.11.1
Requires-Dist: python-dateutil>=2.8.2
Requires-Dist: requests>=2.31.0
Requires-Dist: sarif-om>=1.0.4
Requires-Dist: urllib3>=2.1.0
Requires-Dist: yara-python==4.3.1
